{"status":"OK","lastPrice":32.85,"bid":32.93,"bidSize":2,"ask":33.01,"askSize":1,"lotSize":100,"volume":26156,"recentTradingDayOpenPrice":32.27,"dayRangeHigh":33.19,"dayRangeLow":32.16,"lastClose":32.44,"priceOfTradeAfter":null,"timeOfTradeAfter":null,"recentTradingDay":"2021-08-20","lastUpdateTime":"2021-08-20T14:34:42.000","recentTradingDayJulian":"20-08-2021","tradingStatus":"Open","marketCap":621197642.2300000191,"dividendYield":0.0060624,"yearRangeHigh":33.99,"yearRangeLow":14.38,"currencyCode":"USD","currencySymbol":"$","listedCurrency":"USD","tradedCurrency":null,"avgVolume":50365.6923076923,"exchangeID":"XNAS","exchangeName":"NASDAQ","exchangeTimeZone":"EST","type":"Equity","ts":"1629484346000","dayChange":0.53,"dayChangePer":1.6399,"bidMarket":"17","askMarket":"19","originationMarket":"18","message":"126.1.PGC","lastUpdateRealTimeDate":"20-08-2021","lastUpdateRealTimeTime":"14:32:26.000","nav":null,"oneDayReturn":null,"navLastDate":null,"navLastDate1":null,"navLastTime":null,"isBats":true}