{"status":"OK","lastPrice":22.227,"bid":22.31,"bidSize":1,"ask":22.6,"askSize":1,"lotSize":100,"volume":1388,"recentTradingDayOpenPrice":22.56,"dayRangeHigh":22.56,"dayRangeLow":22.227,"lastClose":22.55,"priceOfTradeAfter":null,"timeOfTradeAfter":null,"recentTradingDay":"2021-07-27","lastUpdateTime":"2021-07-27T11:10:27.000","recentTradingDayJulian":"27-07-2021","tradingStatus":"Open","marketCap":216390225.0090000033,"dividendYield":0.0431907,"yearRangeHigh":24.89,"yearRangeLow":15.13,"currencyCode":"USD","currencySymbol":"$","listedCurrency":"USD","tradedCurrency":null,"avgVolume":41703.359375,"exchangeID":"XNAS","exchangeName":"NASDAQ","exchangeTimeZone":"EST","type":"Equity","ts":"1627398628000","dayChange":-0.323,"dayChangePer":-1.4324,"bidMarket":"8","askMarket":"19","originationMarket":"18","message":"126.1.WEYS","lastUpdateRealTimeDate":"27-07-2021","lastUpdateRealTimeTime":"11:10:28.000","nav":null,"oneDayReturn":null,"navLastDate":null,"navLastDate1":null,"navLastTime":null,"isBats":true}