{"status":"OK","lastPrice":53.11,"bid":46.55,"bidSize":2,"ask":56,"askSize":3,"lotSize":100,"volume":409554,"recentTradingDayOpenPrice":54.39,"dayRangeHigh":54.39,"dayRangeLow":52.695,"lastClose":55.07,"priceOfTradeAfter":52.7,"timeOfTradeAfter":"2021-08-17T19:56:09.000","recentTradingDay":"2021-08-17","lastUpdateTime":"2021-08-17T19:00:01.000","recentTradingDayJulian":"17-08-2021","tradingStatus":"Closed","marketCap":2088859159.7699999809,"dividendYield":0.0771983,"yearRangeHigh":78.35,"yearRangeLow":36.9,"currencyCode":"USD","currencySymbol":"$","listedCurrency":"USD","tradedCurrency":null,"avgVolume":448573.7846153846,"exchangeID":"XNYS","exchangeName":"New York Stock Exchange","exchangeTimeZone":"EST","type":"Equity","ts":"1629248477000","dayChange":-1.96,"dayChangePer":-3.5591,"bidMarket":"16","askMarket":"16","originationMarket":"16","message":"126.1.BCC","lastUpdateRealTimeDate":"17-08-2021","lastUpdateRealTimeTime":"21:01:17.000","nav":null,"oneDayReturn":null,"navLastDate":null,"navLastDate1":null,"navLastTime":null,"isBats":true}