{"status":"OK","lastPrice":15.445,"bid":15.33,"bidSize":2,"ask":15.45,"askSize":7,"lotSize":100,"volume":1053,"recentTradingDayOpenPrice":15.32,"dayRangeHigh":15.445,"dayRangeLow":15.32,"lastClose":15.45,"priceOfTradeAfter":null,"timeOfTradeAfter":null,"recentTradingDay":"2021-08-20","lastUpdateTime":"2021-08-20T14:07:14.000","recentTradingDayJulian":"20-08-2021","tradingStatus":"Open","marketCap":50316087.7550000027,"dividendYield":null,"yearRangeHigh":15.45,"yearRangeLow":15.32,"currencyCode":"USD","currencySymbol":"$","listedCurrency":"USD","tradedCurrency":null,"avgVolume":0,"exchangeID":"XNAS","exchangeName":"NASDAQ","exchangeTimeZone":"EST","type":"Equity","ts":"1629482835000","dayChange":-0.005,"dayChangePer":-0.0324,"bidMarket":"12","askMarket":"12","originationMarket":"19","message":"126.1.TCBS","lastUpdateRealTimeDate":"20-08-2021","lastUpdateRealTimeTime":"14:07:15.000","nav":null,"oneDayReturn":null,"navLastDate":null,"navLastDate1":null,"navLastTime":null,"isBats":true}