{"_meta":{"companyId":"0C000098V0","statementType":"income-statement","periodReport":"Success","latestReport":"Success"},"columnDefs":["2011","2012","2013","2014","2015","2016","2017","2018","2019","2020","TTM"],"filingIdList":[null,null,null,null,null,"126415682","159940592","209211171","262087834","319015895",null],"rows":[{"parentId":"","label":"IncomeStatement","dataPointId":"IFIS000000","order":385,"subLevel":[{"parentId":"IFIS000000385","label":"Gross Profit","dataPointId":"IFIS000590","order":386,"datum":["_PO_","_PO_","_PO_","_PO_","_PO_",23.85,35.20,46.48,57.93,69.27,76.04],"subLevel":[{"parentId":"IFIS000590386","label":"Total Revenue","dataPointId":"IFIS001170","order":387,"collapsed":true,"datum":["_PO_","_PO_","_PO_","_PO_","_PO_",27.64,40.65,55.84,70.70,85.97,94.40],"subLevel":[{"parentId":"IFIS001170387","label":"Business Revenue","dataPointId":"IFIS001839","order":388,"collapsed":true,"datum":["_PO_","_PO_","_PO_","_PO_","_PO_",26.89,39.94,55.01,69.66,84.17,92.17]},{"parentId":"IFIS001170387","label":"Other Revenue","dataPointId":"IFIS002228","order":391,"collapsed":true,"datum":["_PO_","_PO_","_PO_","_PO_","_PO_",0.75,0.71,0.83,1.04,1.80,2.23]}]},{"parentId":"IFIS000590386","label":"Cost of Revenue","dataPointId":"IFIS000200","order":392,"datum":["_PO_","_PO_","_PO_","_PO_","_PO_",-3.79,-5.45,-9.36,-12.77,-16.69,-18.36]}]},{"parentId":"IFIS000000385","label":"Operating Income/Expenses","dataPointId":"IFIS001220","order":405,"datum":["_PO_","_PO_","_PO_","_PO_","_PO_",-11.42,-15.00,-21.57,-33.94,-36.60,-37.88],"subLevel":[{"parentId":"IFIS001220405","label":"Selling, General and Administrative Expenses","dataPointId":"IFIS001700","order":406,"datum":["_PO_","_PO_","_PO_","_PO_","_PO_",-5.50,-7.24,-11.30,-20.34,-18.16,-18.25],"subLevel":[{"parentId":"IFIS001700406","label":"General and Administrative Expenses","dataPointId":"IFIS000040","order":414,"collapsed":true,"datum":["_PO_","_PO_","_PO_","_PO_","_PO_",-1.73,-2.52,-3.45,-10.47,-6.56,-6.60]},{"parentId":"IFIS001700406","label":"Selling and Marketing Expenses","dataPointId":"IFIS001690","order":428,"collapsed":true,"datum":["_PO_","_PO_","_PO_","_PO_","_PO_",-3.77,-4.73,-7.85,-9.88,-11.59,-11.65]}]},{"parentId":"IFIS001220405","label":"Research and Development Expenses","dataPointId":"IFIS001620","order":431,"collapsed":true,"datum":["_PO_","_PO_","_PO_","_PO_","_PO_",-5.92,-7.75,-10.27,-13.60,-18.45,-19.63]}]},{"parentId":"IFIS000000385","label":"Total Operating Profit/Loss","dataPointId":"IFIS001230","order":446,"collapsed":true,"datum":["_PO_","_PO_","_PO_","_PO_","_PO_",12.43,20.20,24.91,23.99,32.67,38.16]},{"parentId":"IFIS000000385","label":"Non-Operating Income/Expenses, Total","dataPointId":"IFIS001917","order":447,"datum":["_PO_","_PO_","_PO_","_PO_","_PO_",0.09,0.39,0.45,0.83,0.51,0.67],"subLevel":[{"parentId":"IFIS001917447","label":"Total Net Finance Income/Expense","dataPointId":"IFIS000930","order":448,"datum":["_PO_","_PO_","_PO_","_PO_","_PO_",0.17,0.39,0.65,0.90,0.67,0.56],"subLevel":[{"parentId":"IFIS000930448","label":"Net Interest Income/Expense","dataPointId":"IFIS002367","order":449,"datum":["_PO_","_PO_","_PO_","_PO_","_PO_",0.17,0.39,0.65,0.90,0.67,0.56],"subLevel":[{"parentId":"IFIS002367449","label":"Interest Income","dataPointId":"IFIS000910","order":456,"collapsed":true,"datum":["_PO_","_PO_","_PO_","_PO_","_PO_",0.18,0.40,0.66,0.92,0.67,0.56]},{"parentId":"IFIS002367449","label":"Interest Expense Net of Capitalized Interest","dataPointId":"IFIS000800","order":450,"datum":["_PO_","_PO_","_PO_","_PO_","_PO_",-0.01,-0.01,-0.01,-0.02,null,null]}]}]},{"parentId":"IFIS001917447","label":"Net Investment Income","dataPointId":"IFIS001915","order":461,"datum":["_PO_","_PO_","_PO_","_PO_","_PO_",-0.08,-0.01,-0.21,-0.11,-0.13,null],"subLevel":[{"parentId":"IFIS001915461","label":"Gain/Loss on Foreign Exchange","dataPointId":"IFIS001882","order":472,"datum":["_PO_","_PO_","_PO_","_PO_","_PO_",-0.08,-0.01,-0.21,-0.11,-0.13,null]}]},{"parentId":"IFIS001917447","label":"Other Income/Expense, Non-Operating","dataPointId":"IFIS200292","order":514,"collapsed":true,"datum":["_PO_","_PO_","_PO_","_PO_","_PO_",0.00,0.01,0.01,0.03,-0.03,0.33]},{"parentId":"IFIS001917447","label":"Irregular Income/Expenses","dataPointId":"IFIS101189","order":480,"datum":["_PO_","_PO_","_PO_","_PO_","_PO_",null,null,null,null,null,null]}]},{"parentId":"IFIS000000385","label":"Pretax Income","dataPointId":"IFIS001490","order":518,"collapsed":true,"datum":["_PO_","_PO_","_PO_","_PO_","_PO_",12.52,20.59,25.36,24.81,33.18,38.82]},{"parentId":"IFIS000000385","label":"Provision for Income Tax","dataPointId":"IFIS001560","order":519,"datum":["_PO_","_PO_","_PO_","_PO_","_PO_",-2.30,-4.66,-3.25,-6.33,-4.03,-5.08]},{"parentId":"IFIS000000385","label":"Net Income from Continuing Operations","dataPointId":"IFIS001110","order":529,"collapsed":true,"datum":["_PO_","_PO_","_PO_","_PO_","_PO_",10.22,15.93,22.11,18.49,29.15,33.74]},{"parentId":"IFIS000000385","label":"Net Income after Extraordinary Items and Discontinued Operations","dataPointId":"IFIS001977","order":535,"collapsed":true,"datum":["_PO_","_PO_","_PO_","_PO_","_PO_",10.22,15.93,22.11,18.49,29.15,33.74]},{"parentId":"IFIS000000385","label":"Net Income after Non-Controlling/Minority Interests","dataPointId":"IFIS001090","order":537,"collapsed":true,"datum":["_PO_","_PO_","_PO_","_PO_","_PO_",10.22,15.93,22.11,18.49,29.15,33.74]},{"parentId":"IFIS000000385","label":"Preferred/Other Stock Distribution","dataPointId":"IFIS001470","order":538,"datum":["_PO_","_PO_","_PO_","_PO_","_PO_",-0.03,-0.01,0.00,0.00,0.00,0.00],"subLevel":[{"parentId":"IFIS001470538","label":"Other Distributions","dataPointId":"IFIS002046","order":541,"collapsed":true,"datum":["_PO_","_PO_","_PO_","_PO_","_PO_",-0.03,-0.01,0.00,0.00,0.00,0.00]}]},{"parentId":"IFIS000000385","label":"Net Income Available to Common Stockholders","dataPointId":"IFIS001100","order":543,"collapsed":true,"datum":["_PO_","_PO_","_PO_","_PO_","_PO_",10.19,15.92,22.11,18.49,29.15,33.74]},{"parentId":"IFIS000000385","label":"Diluted Net Income Available to Common Stockholders","dataPointId":"IFIS002230","order":545,"collapsed":true,"datum":["_PO_","_PO_","_PO_","_PO_","_PO_",10.22,15.93,22.11,18.49,29.15,33.72]},{"parentId":"IFIS000000385","label":"Income Statement Supplemental Section","dataPointId":"IFIS002156","order":560,"datum":["_PO_","_PO_","_PO_","_PO_","_PO_",null,null,null,null,null,null],"subLevel":[{"parentId":"IFIS002156560","label":"Reported Normalized and Operating Income/Expense Supplemental Section","dataPointId":"IFIS003147","order":561,"datum":["_PO_","_PO_","_PO_","_PO_","_PO_",null,null,null,null,null,null],"subLevel":[{"parentId":"IFIS003147561","label":"Total Revenue as Reported, Supplemental","dataPointId":"IFIS003203","order":562,"collapsed":true,"datum":["_PO_","_PO_","_PO_","_PO_","_PO_",27.64,40.65,55.84,70.70,85.97,94.40]},{"parentId":"IFIS003147561","label":"Total Operating Profit/Loss as Reported, Supplemental","dataPointId":"IFIS003138","order":564,"collapsed":true,"datum":["_PO_","_PO_","_PO_","_PO_","_PO_",12.43,20.20,24.91,23.99,32.67,38.16]},{"parentId":"IFIS003147561","label":"Reported Effective Tax Rate","dataPointId":"IFIS002303","order":566,"collapsed":true,"datum":["_PO_","_PO_","_PO_","_PO_","_PO_",0.18,0.23,0.13,0.255,0.122,null]},{"parentId":"IFIS003147561","label":"Reported Normalized Income","dataPointId":"IFIS002229","order":565,"collapsed":true,"datum":["_PO_","_PO_","_PO_","_PO_","_PO_",12.37,null,null,null,null,null]},{"parentId":"IFIS003147561","label":"Reported Normalized Operating Profit","dataPointId":"IFIS003202","order":572,"collapsed":true,"datum":["_PO_","_PO_","_PO_","_PO_","_PO_",16.49,null,null,null,null,null]}]},{"parentId":"IFIS002156560","label":"Operating Income/Expenses, Supplemental Section","dataPointId":"IFIS001905","order":575,"datum":["_PO_","_PO_","_PO_","_PO_","_PO_",null,null,null,null,null,null],"subLevel":[{"parentId":"IFIS001905575","label":"Depreciation, Amortization and Depletion, Supplemental","dataPointId":"IFIS200330","order":589,"datum":["_PO_","_PO_","_PO_","_PO_","_PO_",null,null,null,null,-7.12,-3.70],"subLevel":[{"parentId":"IFIS200330589","label":"Depreciation and Amortization, Supplemental","dataPointId":"IFIS002143","order":590,"datum":["_PO_","_PO_","_PO_","_PO_","_PO_",null,null,null,null,-7.12,-3.70],"subLevel":[{"parentId":"IFIS002143590","label":"Depreciation, Supplemental","dataPointId":"IFIS002144","order":591,"collapsed":true,"datum":["_PO_","_PO_","_PO_","_PO_","_PO_",null,null,null,null,-6.65,-3.46]},{"parentId":"IFIS002143590","label":"Amortization, Supplemental","dataPointId":"IFIS002137","order":592,"collapsed":true,"datum":["_PO_","_PO_","_PO_","_PO_","_PO_",null,null,null,null,-0.47,-0.24]}]}]}]}]},{"parentId":"IFIS000000385","label":"Dilution to Earnings","dataPointId":"IFIS101211","order":544,"collapsed":true,"datum":["_PO_","_PO_","_PO_","_PO_","_PO_",0.03,0.01,0.00,0.00,null,-0.02]}]},{"parentId":"","label":"WasoAndEpsData","dataPointId":"SAL0001000","collapsed":false,"subLevel":[{"parentId":"SAL0001000","label":"Basic EPS","dataPointId":"SAL0001001","collapsed":true,"datum":["_PO_","_PO_","_PO_","_PO_","_PO_",3.5600,5.4900,7.6500,6.4800,10.2200,11.8400]},{"parentId":"SAL0001000","label":"Diluted EPS","dataPointId":"SAL0001002","collapsed":true,"datum":["_PO_","_PO_","_PO_","_PO_","_PO_",3.490000,5.390000,7.570000,6.430000,10.090000,11.680000]},{"parentId":"SAL0001000","label":"Basic WASO","dataPointId":"SAL0001003","collapsed":true,"datum":["_PO_","_PO_","_PO_","_PO_","_PO_",2.86,2.90,2.89,2.85,2.85,2.85]},{"parentId":"SAL0001000","label":"Diluted WASO","dataPointId":"SAL0001004","collapsed":true,"datum":["_PO_","_PO_","_PO_","_PO_","_PO_",2.93,2.96,2.92,2.88,2.89,2.89]}]}],"footer":{"currency":"USD","currencySymbol":"$","orderOfMagnitude":"Billion","fiscalYearEndDate":"12-31"},"userType":"Free"}