{"Collapsed":{"rows":[{"label":"Price/Sales","salDataId":"price.sales.label","isQuantitative":false,"datum":["0.5099","0.6221","0.7589","0.6787","0.3468","0.739","1.0132","0.9533","1.044","0.8118","0.6673","0.8951","3.1148"],"subLevel":""},{"label":"Price/Earnings","salDataId":"price.earnings.label","isQuantitative":false,"datum":["52.7692",null,null,null,null,null,"58.2813","29.2059","19.8362",null,"443.0","64.2398","26.0078"],"subLevel":""},{"label":"Price/Cash Flow","salDataId":"price.cash.flow.label","isQuantitative":false,"datum":["4.6854","9.5277","8.9934","7.3372","4.8866","7.9652","11.116","8.7786","12.8541",null,"30.8179","15.8268","17.5408"],"subLevel":""},{"label":"Price/Book","salDataId":"price.book.label","isQuantitative":false,"datum":["1.1432","2.3326","4.1408","2.8205","2.7454","4.3456","8.9829","6.04","2.5599","1.9867","2.0234","5.7199","4.3465"],"subLevel":""}],"columnDefs":["Calendar","2011","2012","2013","2014","2015","2016","2017","2018","2019","2020","Current","5-Yr","Index"],"columnDefs_labels":["tabular.data.label.column.year","2011","2012","2013","2014","2015","2016","2017","2018","2019","2020","valuation.headers.current","valuation.headers.fiveyear","valuation.headers.index"],"userType":null,"footer":{"asOfLabel":"As of","asOfDate":"2021-08-19T00:00:00.000","indexLabel":"Index:","indexName":"Morningstar US Market TR USD","enterpriseValueCurrency":"USD"}},"Expanded":{"rows":[{"label":"Price/Forward Earnings","salDataId":"price.forward.earnings.label","isQuantitative":false,"datum":["12.5156","19.3424","28.8184","15.748","15.748","28.3286","25.1889",null,"13.624","23.2019","21.3675","21.8216",null],"subLevel":""},{"label":"PEG Ratio","salDataId":"peg.ratio.label","isQuantitative":false,"datum":["0.8343","1.6118","2.8202","1.5403",null,null,null,null,null,"2.32","2.1349",null,null],"subLevel":""},{"label":"Earnings Yield %","salDataId":"earnings.yield.label","isQuantitative":false,"datum":["1.9","-13.4","-20.59","-0.32","-5.2","-7.13","1.72","3.42","5.04","-1.78","0.23","0.22",null],"subLevel":""},{"label":"Enterprise Value (Bil)","salDataId":"enterprise.value.label","isQuantitative":false,"datum":["2.47","2.77","3.21","2.27","1.43","1.69","2.06","2.16","2.55","2.69","2.76","2.25",null],"subLevel":"","orderOfMagnitude":"Bil"},{"label":"Enterprise Value/EBIT","salDataId":"enterprise.value.ebit.label","isQuantitative":false,"datum":["27.0498",null,null,"30.411","29.2198",null,"21.6255","11.5112","14.9753","65.1761","31.2997","72.8566",null],"subLevel":""},{"label":"Enterprise Value/EBITDA","salDataId":"enterprise.value.ebitda.label","isQuantitative":false,"datum":["6.1275","27.4027",null,"8.9202","6.7916","12.6935","9.1284","6.7474","8.3681","13.6771","10.8957","10.197",null],"subLevel":""}],"columnDefs":["Calendar","2011","2012","2013","2014","2015","2016","2017","2018","2019","2020","Current","5-Yr","Index"],"columnDefs_labels":["tabular.data.label.column.year","2011","2012","2013","2014","2015","2016","2017","2018","2019","2020","valuation.headers.current","valuation.headers.fiveyear","valuation.headers.index"]}}